flask_sqlalchemy_core/__init__.py
tests/__init__.py
tests/conftest.py
tests/test_basic_usage.py
tests/utils.py
flask_sqlalchemy_core-0.1.1.dist-info/METADATA
flask_sqlalchemy_core-0.1.1.dist-info/WHEEL
flask_sqlalchemy_core-0.1.1.dist-info/top_level.txt
flask_sqlalchemy_core-0.1.1.dist-info/RECORD
