Metadata-Version: 1.1
Name: flask-sqlalchemy-core
Version: 0.1.1
Summary: SQLAlchemy Core integration for Flask
Home-page: https://github.com/rshk/flask-sqlalchemy-core
Author: Samuele Santi
Author-email: samuele@samuelesanti.com
License: BSD License
Platform: UNKNOWN
Classifier: License :: OSI Approved :: BSD License
Classifier: Programming Language :: Python :: 3.6
Classifier: Programming Language :: Python :: 3.7
Classifier: Programming Language :: Python :: 3 :: Only
